fengyong/Assembler.py
fengyong/DisAssembler.py
fengyong/Interpreter.py
fengyong/Memory.py
fengyong/Preprocessor.py
fengyong/RegData.py
fengyong/Registers.py
fengyong/Simulator.py
fengyong/__init__.py
fengyong/instructions.py
fengyong/static.py
fengyong-1.2.0.dist-info/LICENSE
fengyong-1.2.0.dist-info/METADATA
fengyong-1.2.0.dist-info/WHEEL
fengyong-1.2.0.dist-info/entry_points.txt
fengyong-1.2.0.dist-info/top_level.txt
fengyong-1.2.0.dist-info/RECORD
