Metadata-Version: 2.1
Name: fengyong
Version: 1.2.0
Summary: Run MIPS with python!
Home-page: https://github.com/CQU-AI/pymips
Author: CQU-AI
Author-email: peter@mail.loopy.tech
Maintainer: loopyme
Maintainer-email: peter@mail.loopy.tech
License: MIT License
Platform: all
Classifier: Development Status :: 4 - Beta
Classifier: Operating System :: OS Independent
Classifier: Intended Audience :: Developers
Classifier: License :: OSI Approved :: MIT License
Classifier: Programming Language :: Python
Classifier: Programming Language :: Python :: Implementation
Classifier: Programming Language :: Python :: 3.6
Classifier: Topic :: Software Development :: Libraries
